mockintosh/__init__.py
mockintosh/__main__.py
mockintosh/builders.py
mockintosh/config.py
mockintosh/constants.py
mockintosh/definition.py
mockintosh/exceptions.py
mockintosh/handlers.py
mockintosh/helpers.py
mockintosh/logs.py
mockintosh/management.py
mockintosh/params.py
mockintosh/performance.py
mockintosh/recognizers.py
mockintosh/replicas.py
mockintosh/schema.json
mockintosh/servers.py
mockintosh/stats.py
mockintosh/templating.py
mockintosh/transpilers.py
mockintosh/hbs/__init__.py
mockintosh/hbs/methods.py
mockintosh/j2/__init__.py
mockintosh/j2/meta.py
mockintosh/j2/methods.py
mockintosh/res/management.html
mockintosh/res/mock.png
mockintosh/res/sample.yml
mockintosh/res/version.txt
mockintosh/services/__init__.py
mockintosh/services/http.py
mockintosh/services/asynchronous/__init__.py
mockintosh/services/asynchronous/_looping.py
mockintosh/services/asynchronous/amazonsqs.py
mockintosh/services/asynchronous/amqp.py
mockintosh/services/asynchronous/gpubsub.py
mockintosh/services/asynchronous/kafka.py
mockintosh/services/asynchronous/mqtt.py
mockintosh/services/asynchronous/redis.py
mockintosh/ssl/cert.pem
mockintosh/ssl/key.pem
mockintosh-0.13.17.dist-info/LICENSE
mockintosh-0.13.17.dist-info/METADATA
mockintosh-0.13.17.dist-info/WHEEL
mockintosh-0.13.17.dist-info/entry_points.txt
mockintosh-0.13.17.dist-info/top_level.txt
mockintosh-0.13.17.dist-info/RECORD
