Metadata-Version: 2.1
Name: mockintosh
Version: 0.13.17
Summary: The API mocking server for microservice environments
Home-page: https://github.com/up9inc/mockintosh
Author: UP9 Inc.
Author-email: support@up9.com
License: MIT
Keywords: mock api json restful automatic web server generator configuration
Platform: UNKNOWN
Classifier: Development Status :: 4 - Beta
Classifier: Intended Audience :: Developers
Classifier: Topic :: Internet :: WWW/HTTP :: HTTP Servers
Classifier: Natural Language :: English
Classifier: Programming Language :: Python :: 3 :: Only
License-File: LICENSE
Requires-Dist: Jinja2 (==2.11.3)
Requires-Dist: Faker (==4.18.0)
Requires-Dist: tornado (>=6.1)
Requires-Dist: PyYAML (>=5.4)
Requires-Dist: jsonschema (==3.2.0)
Requires-Dist: pybars4 (>=0.9.11)
Requires-Dist: accept-types (==0.4.1)
Requires-Dist: jsonpath-ng (==1.5.2)
Requires-Dist: httpx (==0.17.1)
Requires-Dist: confluent-kafka (>=1.6.1)
Requires-Dist: prance[osv] (>=0.21.2)
Requires-Dist: pika (>=1.2.0)
Requires-Dist: PyRSMQ (>=0.4.5)
Requires-Dist: paho-mqtt (>=1.5.1)
Requires-Dist: graphql-core (>=3.1.5)
Provides-Extra: cloud
Requires-Dist: google-cloud-pubsub (>=2.5.0) ; extra == 'cloud'
Requires-Dist: boto3 (>=1.17.97) ; extra == 'cloud'
Provides-Extra: dev
Requires-Dist: flake8 ; extra == 'dev'
Requires-Dist: psutil ; extra == 'dev'
Requires-Dist: pytest ; extra == 'dev'
Requires-Dist: coverage ; extra == 'dev'
Requires-Dist: codecov ; extra == 'dev'
Requires-Dist: openapi-spec-validator ; extra == 'dev'
Requires-Dist: backports-datetime-fromisoformat ; extra == 'dev'
Requires-Dist: pytest-travis-fold ; extra == 'dev'
